[
  {
    "ingredient": {
      "type": "item",
      "code": "game:ingot-legendary"
    },
    "pattern": [
      [
        "#####",
        "#####",
        "_###_",
        "__#__"
      ],
      [
        "#####",
        "_###_",
        "__#__",
        "_____"
      ]
    ],
    "name": "Legendary Hoe",
    "output": {
      "type": "item",
      "code": "legendarymobs:legendarysword-hoe-2-rough"
    }
  },
  {
    "ingredient": {
      "type": "item",
      "code": "game:ingot-legendary"
    },
    "pattern": [
      [
        "#_#_#",
        "#_#_#",
        "#_#_#",
        "#####"
      ],
      [
        "_____",
        "_____",
        "_____",
        "#####"
      ]
    ],
    "name": "Legendary Hoe",
    "output": {
      "type": "item",
      "code": "legendarymobs:legendarysword-hoe-1-rough"
    }
  }
]