{"GameVersion":"1.10.0-dev.2","SizeX":3,"SizeY":4,"SizeZ":3,"BlockCodes":{"1856":"meta-underground","1798":"planks-aged-hor","1032":"chest-east"},"ItemCodes":{"88":"metalplate-lead","86":"metalplate-gold","528":"gear-temporal"},"Indices":[2098176,1025,1049601,2097153,2098177,2099201,3146753,2098178],"BlockIds":[1856,1856,1798,1856,1032,1856,1856,1856],"BlockEntities":{"2098177":"!<d@[F*OsR\"98H*E,TfC\"onW'!<d@[F*b*T\"98W4Bl8**DKKf;Gl\\+hF)5c:EsMaG!!WUJCi=E:#6?LY!<<*\"=9&=$!WW3#!!`NZ!!*'\"!*0(\"!!3-#!!!6)1&q=T!!!Q3!!!$\"z!!NdCDfS0\\De!QMDe*Dd@q]FpF=h'4F*%QgFEqh:$=e!jCgh:(ARmRs"},"Entities":[],"ReplaceMode":2}